viur/toolkit/__init__.py
viur/toolkit/callable_tasks.py
viur/toolkit/checks.py
viur/toolkit/context.py
viur/toolkit/db.py
viur/toolkit/decorators.py
viur/toolkit/helpers.py
viur/toolkit/memcache.py
viur/toolkit/numeric.py
viur/toolkit/property.py
viur/toolkit/report.py
viur/toolkit/version.py
viur/toolkit/viur.py
viur/toolkit/importer/__init__.py
viur/toolkit/importer/importable.py
viur/toolkit/importer/importer.py
viur_toolkit-0.7.1.dist-info/licenses/LICENSE
viur_toolkit-0.7.1.dist-info/METADATA
viur_toolkit-0.7.1.dist-info/WHEEL
viur_toolkit-0.7.1.dist-info/top_level.txt
viur_toolkit-0.7.1.dist-info/RECORD
