Metadata-Version: 2.4
Name: viur-toolkit
Version: 0.7.1
Summary: A kit of helpers and tools to simplify more intensive use of ViUR
Author-email: Sven Eberth <se@mausbrand.de>
Maintainer-email: Sven Eberth <se@mausbrand.de>
License: MIT License
Project-URL: Repository, https://github.com/viur-framework/viur-toolkit.git
Project-URL: Bug Tracker, https://github.com/viur-framework/viur-toolkit/issues
Keywords: viur,plugin,backend,toolkit
Classifier: Intended Audience :: Developers
Classifier: License :: OSI Approved :: MIT License
Classifier: Operating System :: OS Independent
Classifier: Programming Language :: Python :: 3.10
Classifier: Programming Language :: Python :: 3.11
Classifier: Programming Language :: Python :: 3.12
Classifier: Topic :: Software Development :: Libraries :: Python Modules
Requires-Python: >=3.10
License-File: LICENSE
Requires-Dist: requests
Requires-Dist: Deprecated
Requires-Dist: viur-core>=3.6
Dynamic: license-file
